{
  "title": "Vaked: Capability-Graph Languages for Deterministic Agentic Systems",
  "authors": [
    {
      "name": "Peter Lodri",
      "affiliation": "Vaked Research",
      "orcid": null
    }
  ],
  "date": "2026-06-17",
  "abstract": "Contemporary agentic AI frameworks rely on probabilistic wrappers and post-hoc monitoring, creating systems whose behavior boundaries are observed rather than enforced. We present Vaked, a capability-graph language and deterministic runtime that replaces hope-based security models with kernel-level enforcement. The system compiles declarative capability specifications into eBPF programs, NixOS modules, and Zig enforcement daemons, producing a mathematically bounded execution environment. A deployed five-node, three-continent swarm demonstrates 27ms intra-continent convergence and sub-second transatlantic gossip synchronization. The Genesis Block, sealed via DNS TXT record with a 256-bit SHA hash, establishes an immutable integrity root.",
  "keywords": [
    "capability-graph",
    "agentic governance",
    "formal verification",
    "deterministic infrastructure",
    "Zig",
    "eBPF",
    "NixOS",
    "P2P gossip",
    "Merkle tree",
    "append-only ledger",
    "kernel-level enforcement",
    "Principle of Least Authority"
  ],
  "domain": "https://vaked.dev",
  "repository": "https://github.com/peterlodri-sec/vaked-base",
  "genesis_seal": "7c242080f5f821e5eaf563fe2208d60632c451687baf65f4fe8e4a0d226e3ecf",
  "genesis_timestamp": "2026-06-16T00:00:00Z",
  "format": "IEEE Computer Society",
  "pages": 8,
  "references": 14,
  "license": "CC BY 4.0"
}
